bohr/__init__.py
bohr/database.py
bohr/mdm.py
bohr/test.py
bohr-0.2.dist-info/METADATA
bohr-0.2.dist-info/WHEEL
bohr-0.2.dist-info/top_level.txt
bohr-0.2.dist-info/RECORD
