Metadata-Version: 2.1
Name: bohr
Version: 0.2
Author: DanC
Author-email: dan.cabrol@bohr-energie.fr
Requires-Dist: psycopg2-binary ==2.9.5
Requires-Dist: psycopg2 ==2.9.6
Requires-Dist: pandas ==2.0.1
